MANIFEST.in
setup.py
r2dto_rdf/__init__.py
r2dto_rdf/errors.py
r2dto_rdf/fields.py
r2dto_rdf/mapping.py
r2dto_rdf/serializer.py
r2dto_rdf/utils.py
r2dto_rdf.egg-info/PKG-INFO
r2dto_rdf.egg-info/SOURCES.txt
r2dto_rdf.egg-info/dependency_links.txt
r2dto_rdf.egg-info/requires.txt
r2dto_rdf.egg-info/top_level.txt