Metadata-Version: 1.1
Name: r2dto-rdf
Version: 0.0.2
Summary: 
